{
  "date": "2011-11-07",
  "title": "Remontée Mécanique",
  "curators": [
    "Stereotype",
    "Trakabs et Eat Rabbit"
  ],
  "cover": "files/remontee-mecanique/source.jpg",
  "tracks": [
    {
      "artist": "Picky Picnic",
      "title": "Hontokana Really"
    },
    {
      "artist": "Lust Sacrifice",
      "title": "Vision Ghost Sailer"
    },
    {
      "artist": "Red Wedding",
      "title": "All (Dressed Up)"
    },
    {
      "artist": "Nejet!nok",
      "title": " Plastic plastic"
    },
    {
      "artist": "Sico et Cloé",
      "title": "Mon ami Sico"
    },
    {
      "artist": "Kozmonaut",
      "title": "Arabisch Nacht Vier Producti"
    },
    {
      "artist": "Began Began",
      "title": "Computer Wars"
    },
    {
      "artist": "Raison Future",
      "title": "Puissance Electronique"
    },
    {
      "artist": "Sympathy Nervous",
      "title": "A Worm"
    },
    {
      "artist": "Klaus Krager",
      "title": "Suchen"
    },
    {
      "artist": "In Sotto Voce",
      "title": "Track 01"
    },
    {
      "artist": "Berlin express",
      "title": "The russians are comming"
    },
    {
      "artist": "Noise Unit",
      "title": "Struktur"
    },
    {
      "artist": "A.D.A.C 8286",
      "title": "Keine kontrolle"
    },
    {
      "artist": "Nervous Gender",
      "title": "Cardinal Newman"
    },
    {
      "artist": "Gina X Performance",
      "title": "Babylon Generation"
    },
    {
      "artist": "Telex",
      "title": "Le fond de l'air est rouge"
    },
    {
      "artist": "Satellite & Atom Cristal",
      "title": "Train De Minuit"
    }
  ]
}
